<?xml version = '1.0' encoding = 'UTF-8'?>
<Relation class="oracle.dbtools.crest.model.design.logical.Relation" name="PERSON LSTSKL" directorySegmentName="seg_0" id="222D1F62-193D-A824-3D66-5AAAA95AB3C8">
<createdBy>raoul</createdBy>
<createdTime>2020-01-19 17:04:39 UTC</createdTime>
<ownerDesignName>HRDocs_DMD</ownerDesignName>
<engineerTo>
<item key="BB56A352-CFD4-1775-3008-87EE414A82CE" value="true"/>
</engineerTo>
<sourcePk>9A11308C-6A90-BDF7-489D-8F0E27FA8121</sourcePk>
<identifying>false</identifying>
<optionalSource>true</optionalSource>
<optionalTarget>false</optionalTarget>
<sourceCardinality>1</sourceCardinality>
<sourceEntity>6476F377-B250-7948-85FB-98346C69FA1B</sourceEntity>
<targetCardinalityString>*</targetCardinalityString>
<targetEntity>4638B2B3-E045-2112-C71E-0F8A78F718D1</targetEntity>
<transferable>true</transferable>
<deleteRule>NO ACTION</deleteRule>
</Relation>