<?xml version = '1.0' encoding = 'UTF-8'?>
<TableProxyOraclev12c class="oracle.dbtools.crest.model.design.storage.oracle.v12c.TableProxyOraclev12c" name="SSPRES" directorySegmentName="seg_0" id="EA66EEC3-1D6E-BFA4-7349-3D58AD6FA795">
<createdBy>raoul</createdBy>
<createdTime>2020-03-10 14:04:02 UTC</createdTime>
<ownerDesignName>HRDocs_DMD</ownerDesignName>
<logging>YES</logging>
<partitionedRowMovement>DISABLE</partitionedRowMovement>
<temporaryChanged>false</temporaryChanged>
<accessDriverType>oracle_loader</accessDriverType>
<rejectLimit></rejectLimit>
<columnProxies itemClass="oracle.dbtools.crest.model.design.storage.oracle.v12c.ColumnProxyOraclev12c">
<ColumnProxy name="SSPRES_LBL" id="F06853AB-1E0E-F4D4-8FCB-C8131B55225F">
<createdBy>raoul</createdBy>
<createdTime>2020-03-10 14:04:02 UTC</createdTime>
<ownerDesignName>HRDocs_DMD</ownerDesignName>
</ColumnProxy>
<ColumnProxy name="SSPRES_ID" id="F2E1CD6F-0AD0-FF3C-5A4F-5DE250EB2AFA">
<createdBy>raoul</createdBy>
<createdTime>2020-03-10 14:04:02 UTC</createdTime>
<ownerDesignName>HRDocs_DMD</ownerDesignName>
<autoIncrementDDL>IDENTITY_CLAUSE</autoIncrementDDL>
<notnullConstraintnameChanged>true</notnullConstraintnameChanged>
</ColumnProxy>
</columnProxies>
<primaryKeys>
<PrimaryKey class="oracle.dbtools.crest.model.design.storage.oracle.v10g.PKProxyOraclev10g" name="SSPRES_PK" id="6871A700-F64A-FF25-B1BB-3CE83260C637">
<createdBy>raoul</createdBy>
<createdTime>2020-03-10 14:04:02 UTC</createdTime>
<ownerDesignName>HRDocs_DMD</ownerDesignName>
<indexSort>SORTED</indexSort>
</PrimaryKey>
</primaryKeys>
<uniqueKeys>
<UniqueKey class="oracle.dbtools.crest.model.design.storage.oracle.v10g.UniqueOraclev10g" name="SSPRES_SSPRES_LBL_UN" id="0FB504CC-F502-8CE2-C52B-A48F41602E19">
<createdBy>raoul</createdBy>
<createdTime>2020-03-10 14:04:02 UTC</createdTime>
<ownerDesignName>HRDocs_DMD</ownerDesignName>
<indexSort>SORTED</indexSort>
</UniqueKey>
</uniqueKeys>
</TableProxyOraclev12c>
